graphcart-0.1.4.dist-info/licenses/LICENSE
visuals/__init__.py
visuals/advanced_plots.py
visuals/basic_plots.py
visuals/core.py
visuals/correlation_plots.py
visuals/interactive_plots.py
visuals/plots_3d.py
visuals/statistical_plots.py
visuals/timeseries_plots.py
visuals/utils.py
graphcart-0.1.4.dist-info/METADATA
graphcart-0.1.4.dist-info/WHEEL
graphcart-0.1.4.dist-info/top_level.txt
graphcart-0.1.4.dist-info/RECORD
