Metadata-Version: 2.4
Name: graphcart
Version: 0.1.4
Summary: A modular, one-stop data visualization package
Home-page: https://github.com/Swaathi-S-M/visuals
Author: Swaathi S M
Author-email: smswaathi@gmail.com
License: MIT
Classifier: Programming Language :: Python :: 3
Classifier: License :: OSI Approved :: MIT License
Classifier: Operating System :: OS Independent
Requires-Python: >=3.8
License-File: LICENSE
Requires-Dist: pandas>=1.2
Requires-Dist: numpy>=1.19
Requires-Dist: matplotlib>=3.4
Requires-Dist: seaborn>=0.11
Requires-Dist: plotly>=5.0
Requires-Dist: streamlit
Dynamic: license-file
